excel_split_zim/__init__.py
excel_split_zim/splitter.py
excel_split_zim-0.1.0.dist-info/METADATA
excel_split_zim-0.1.0.dist-info/WHEEL
excel_split_zim-0.1.0.dist-info/RECORD
