Metadata-Version: 2.4
Name: excel_split_zim
Version: 0.1.0
Summary: 一个简单的Excel工作表拆分工具
Author-email: Zim Mu <sufer76980@163.com>
License-Expression: MIT
Classifier: License :: OSI Approved :: MIT License
Classifier: Operating System :: OS Independent
Classifier: Programming Language :: Python :: 3
Requires-Python: >=3.6
Requires-Dist: openpyxl>=3.0.0
